{"name":"终端应用","slug":"终端应用","count":1,"postlist":[{"title":"ZeroTermux","uid":"d914e46ef3958b719ad4bcaf4d26562a","slug":"zerotermux","date":"2022-05-01T01:13:53.000Z","updated":"2022-05-01T02:28:34.802Z","comments":true,"path":"api/articles/zerotermux.json","keywords":null,"cover":"https://s3.bmp.ovh/imgs/2022/05/01/613129a5eee9931e.jpg","text":"简介Termux 是一个 Android 下一个高级的终端模拟器，开源且不需要 root，支持 apt 管理软件包，十分方便安装软件包，完美支持 Python、 PHP、 Ruby、 Nodejs、 MySQL等。随着智能设备的普及和性能的不断提升，如今的手机、平板等的硬件标准已...","link":"","photos":[],"count_time":{"symbolsCount":345,"symbolsTime":"1 mins."},"categories":[],"tags":[{"name":"终端应用","slug":"终端应用","count":1,"path":"api/tags/终端应用.json"}],"author":{"name":"PbShare","slug":"blog-author","avatar":"https://s3.bmp.ovh/imgs/2022/04/24/d659dbe8aedd82f1.jpg","link":"/","description":"您的支持是我最大的动力(o^^o)","socials":{"github":"https://github.com/pbdays","twitter":"https://twitter.com/TomorrowX6","stackoverflow":"","wechat":"","qq":"","weibo":"","zhihu":"","csdn":"","juejin":"","customs":{}}},"feature":true}]}